_pmcxcl.cpython-312-darwin.so
pmcxcl/__init__.py
pmcxcl/bench.py
pmcxcl-0.4.0.dist-info/METADATA
pmcxcl-0.4.0.dist-info/WHEEL
pmcxcl-0.4.0.dist-info/top_level.txt
pmcxcl-0.4.0.dist-info/RECORD
