Metadata-Version: 2.1
Name: pmcxcl
Version: 0.4.0
Summary: Python bindings for Monte Carlo eXtreme (OpenCL) photon transport simulator
Home-page: https://github.com/fangq/mcxcl
Author: Matin Raayai Ardakani, Qianqian Fang
Author-email: raayaiardakani.m@northeastern.edu, q.fang@neu.edu
Maintainer: Qianqian Fang
License: GPLv3+
Download-URL: https://mcx.space
Keywords: Monte Carlo simulation,Biophotonics,Ray-tracing,Rendering,GPU,Modeling,Biomedical Optics,Tissue Optics,Simulator,Optics,OpenCL
Platform: UNKNOWN
Classifier: Development Status :: 4 - Beta
Classifier: Intended Audience :: Science/Research
Classifier: Environment :: GPU
Classifier: Topic :: Scientific/Engineering :: Physics
Classifier: License :: OSI Approved :: GNU General Public License v3 or later (GPLv3+)
Classifier: Programming Language :: Python :: 3.6
Classifier: Programming Language :: Python :: 3.7
Classifier: Programming Language :: Python :: 3.8
Classifier: Programming Language :: Python :: 3.9
Classifier: Programming Language :: Python :: 3.10
Classifier: Programming Language :: Python :: 3.11
Classifier: Programming Language :: Python :: 3.12
Classifier: Programming Language :: Python :: 3.13
Requires: numpy
Requires-Python: >=3.6
